c2cwsgiutils/__init__.py
c2cwsgiutils/acceptance/__init__.py
c2cwsgiutils/acceptance/connection.py
c2cwsgiutils/acceptance/image.py
c2cwsgiutils/acceptance/package-lock.json
c2cwsgiutils/acceptance/package.json
c2cwsgiutils/acceptance/print.py
c2cwsgiutils/acceptance/screenshot.js
c2cwsgiutils/acceptance/utils.py
c2cwsgiutils/auth.py
c2cwsgiutils/broadcast/__init__.py
c2cwsgiutils/broadcast/interface.py
c2cwsgiutils/broadcast/local.py
c2cwsgiutils/broadcast/redis.py
c2cwsgiutils/broadcast/utils.py
c2cwsgiutils/client_info.py
c2cwsgiutils/config_utils.py
c2cwsgiutils/coverage_setup.py
c2cwsgiutils/db.py
c2cwsgiutils/db_maintenance_view.py
c2cwsgiutils/debug/__init__.py
c2cwsgiutils/debug/_listeners.py
c2cwsgiutils/debug/_views.py
c2cwsgiutils/debug/utils.py
c2cwsgiutils/errors.py
c2cwsgiutils/health_check.py
c2cwsgiutils/index.py
c2cwsgiutils/loader.py
c2cwsgiutils/logging_view.py
c2cwsgiutils/models_graph.py
c2cwsgiutils/pretty_json.py
c2cwsgiutils/profiler.py
c2cwsgiutils/prometheus.py
c2cwsgiutils/py.typed
c2cwsgiutils/pyramid.py
c2cwsgiutils/pyramid_logging.py
c2cwsgiutils/redis_stats.py
c2cwsgiutils/redis_utils.py
c2cwsgiutils/request_tracking/__init__.py
c2cwsgiutils/request_tracking/_sql.py
c2cwsgiutils/scripts/__init__.py
c2cwsgiutils/scripts/genversion.py
c2cwsgiutils/scripts/stats_db.py
c2cwsgiutils/scripts/test_print.py
c2cwsgiutils/sentry.py
c2cwsgiutils/services.py
c2cwsgiutils/setup_process.py
c2cwsgiutils/sql_profiler/__init__.py
c2cwsgiutils/sql_profiler/_impl.py
c2cwsgiutils/sqlalchemylogger/README.md
c2cwsgiutils/sqlalchemylogger/__init__.py
c2cwsgiutils/sqlalchemylogger/_filters.py
c2cwsgiutils/sqlalchemylogger/_models.py
c2cwsgiutils/sqlalchemylogger/examples/example.py
c2cwsgiutils/sqlalchemylogger/handlers.py
c2cwsgiutils/static/favicon-16x16.png
c2cwsgiutils/static/favicon-32x32.png
c2cwsgiutils/stats_pyramid/__init__.py
c2cwsgiutils/stats_pyramid/_db_spy.py
c2cwsgiutils/stats_pyramid/_pyramid_spy.py
c2cwsgiutils/templates/index.html.mako
c2cwsgiutils-6.1.8.dist-info/LICENSE
c2cwsgiutils-6.1.8.dist-info/METADATA
c2cwsgiutils-6.1.8.dist-info/WHEEL
c2cwsgiutils-6.1.8.dist-info/entry_points.txt
c2cwsgiutils-6.1.8.dist-info/RECORD
