Metadata-Version: 2.1
Name: c2cwsgiutils
Version: 6.1.8
Summary: Common utilities for Camptocamp WSGI applications
Home-page: https://github.com/camptocamp/c2cwsgiutils
License: BSD-2-Clause
Keywords: geo,gis,sqlalchemy,orm,wsgi
Author: Camptocamp
Author-email: info@camptocamp.com
Requires-Python: >=3.10
Classifier: Development Status :: 5 - Production/Stable
Classifier: Environment :: Plugins
Classifier: Framework :: Pyramid
Classifier: Intended Audience :: Developers
Classifier: Intended Audience :: Information Technology
Classifier: License :: OSI Approved :: BSD License
Classifier: Operating System :: OS Independent
Classifier: Programming Language :: Python
Classifier: Programming Language :: Python :: 3
Classifier: Programming Language :: Python :: 3.10
Classifier: Programming Language :: Python :: 3.11
Classifier: Programming Language :: Python :: 3.12
Classifier: Programming Language :: Python :: 3.13
Classifier: Topic :: Internet :: WWW/HTTP :: WSGI :: Application
Classifier: Typing :: Typed
Provides-Extra: alembic
Provides-Extra: all
Provides-Extra: broadcast
Provides-Extra: debug
Provides-Extra: dev
Provides-Extra: oauth2
Provides-Extra: sentry
Provides-Extra: standard
Provides-Extra: test-images
Provides-Extra: tests
Provides-Extra: webserver
Requires-Dist: SQLAlchemy ; extra == "standard" or extra == "webserver" or extra == "all"
Requires-Dist: SQLAlchemy-Utils ; extra == "standard" or extra == "webserver" or extra == "all"
Requires-Dist: alembic ; extra == "standard" or extra == "alembic" or extra == "all"
Requires-Dist: boltons ; extra == "tests" or extra == "all"
Requires-Dist: cee_syslog_handler
Requires-Dist: cornice ; extra == "standard" or extra == "webserver" or extra == "all"
Requires-Dist: gunicorn ; extra == "standard" or extra == "webserver" or extra == "all"
Requires-Dist: lxml ; extra == "tests" or extra == "all"
Requires-Dist: objgraph ; extra == "debug" or extra == "all"
Requires-Dist: prometheus-client ; extra == "standard" or extra == "webserver" or extra == "all"
Requires-Dist: psycopg2 ; extra == "standard" or extra == "webserver" or extra == "all"
Requires-Dist: pyjwt ; extra == "standard" or extra == "oauth2" or extra == "all"
Requires-Dist: pyramid ; extra == "standard" or extra == "webserver" or extra == "all"
Requires-Dist: pyramid-tm ; extra == "standard" or extra == "webserver" or extra == "all"
Requires-Dist: pyramid_mako ; extra == "standard" or extra == "webserver" or extra == "all"
Requires-Dist: pyyaml
Requires-Dist: redis ; extra == "standard" or extra == "broadcast" or extra == "all"
Requires-Dist: requests
Requires-Dist: requests-oauthlib ; extra == "standard" or extra == "oauth2" or extra == "all"
Requires-Dist: scikit-image ; extra == "test-images"
Requires-Dist: sentry-sdk ; extra == "standard" or extra == "sentry" or extra == "all"
Requires-Dist: ujson
Requires-Dist: urllib3
Requires-Dist: waitress ; extra == "dev" or extra == "all"
Requires-Dist: zope.interface ; extra == "standard" or extra == "webserver" or extra == "all"
Requires-Dist: zope.sqlalchemy ; extra == "standard" or extra == "webserver" or extra == "all"
Project-URL: Repository, https://github.com/camptocamp/c2cwsgiutils
